deloop/__init__.py
deloop/__main__.py
deloop/cli.py
deloop/delooper.py
deloop-0.1.0.dist-info/LICENSE
deloop-0.1.0.dist-info/METADATA
deloop-0.1.0.dist-info/WHEEL
deloop-0.1.0.dist-info/entry_points.txt
deloop-0.1.0.dist-info/top_level.txt
deloop-0.1.0.dist-info/RECORD
