Metadata-Version: 2.2
Name: deloop
Version: 0.1.0
Summary: A simple command-line tool to deloop wav files generated by an audio looper.
Author-email: Alexandre Dareau <alexandre.dareau@protonmail.com>
Maintainer-email: Alexandre Dareau <alexandre.dareau@protonmail.com>
License: GPL-3.0-or-later
Project-URL: Homepage, https://github.com/adareau/deloop
Project-URL: Repository, https://github.com/adareau/deloop.git
Project-URL: Issues, https://github.com/adareau/deloop/issues
Keywords: looper,music,SP-404,wav
Classifier: Development Status :: 4 - Beta
Classifier: Intended Audience :: End Users/Desktop
Classifier: Topic :: Multimedia :: Sound/Audio :: Editors
Classifier: Programming Language :: Python :: 3
Classifier: Programming Language :: Python :: 3.10
Requires-Python: >=3.12
License-File: LICENSE
Requires-Dist: typer==0.15.1
